byted_overpass_data_byteair_sql_service/__init__.py
byted_overpass_data_byteair_sql_service-0.0.1.dist-info/METADATA
byted_overpass_data_byteair_sql_service-0.0.1.dist-info/WHEEL
byted_overpass_data_byteair_sql_service-0.0.1.dist-info/top_level.txt
byted_overpass_data_byteair_sql_service-0.0.1.dist-info/RECORD
